.gitignore
CHANGES.rst
HOWTO.rst
LICENSE
MANIFEST.in
README.rst
deploy.py
requirements.txt
setup.py
upgrade_requirements.txt
colimit/__init__.py
colimit/da.gpx
colimit/hda.gpx
colimit/limits.py
colimit/location.py
colimit/speed.py
colimit/testing.py
colimit/way.py
colimit.egg-info/PKG-INFO
colimit.egg-info/SOURCES.txt
colimit.egg-info/dependency_links.txt
colimit.egg-info/requires.txt
colimit.egg-info/top_level.txt
doc/sphinx/conf.py
doc/sphinx/demo.py
doc/sphinx/doc.rst
doc/sphinx/index.rst
doc/sphinx/intro.rst
doc/sphinx/logo.png
doc/sphinx/releases.rst
doc/sphinx/tutorial.rst
doc/sphinx/api/colimit.rst
test/__init__.py
test/unittests.py