Metadata-Version: 2.1
Name: colimit
Version: 0.1.13
Summary: better know your limits
Home-page: https://sonntagsgesicht.github.com/colimit
Author: sonntagsgesicht
Author-email: sonntagsgesicht@icloud.com
License: No License - only for h_da staff or students
Platform: any
Classifier: Development Status :: 4 - Beta
Classifier: Intended Audience :: Education
Classifier: Intended Audience :: Developers
Classifier: License :: OSI Approved :: Apache Software License
Classifier: Operating System :: OS Independent
Classifier: Programming Language :: Python
Classifier: Programming Language :: Python :: 3.7
Classifier: Programming Language :: Python :: 3.8
Classifier: Programming Language :: Python :: 3.9
Classifier: Programming Language :: Python :: 3.10
Classifier: Topic :: Education
Classifier: Topic :: Software Development
License-File: LICENSE
